AUTHORS.rst
LICENSE
MANIFEST.in
README.rst
requirements.txt
setup.cfg
setup.py
teampass_cli.egg-info/PKG-INFO
teampass_cli.egg-info/SOURCES.txt
teampass_cli.egg-info/dependency_links.txt
teampass_cli.egg-info/entry_points.txt
teampass_cli.egg-info/requires.txt
teampass_cli.egg-info/top_level.txt
tpcli/__init__.py
tpcli/cli.py
tpcli/commands/__init__.py
tpcli/commands/cmd_add.py
tpcli/commands/cmd_edit.py
tpcli/commands/cmd_list.py
tpcli/commands/cmd_remove.py
tpcli/commands/cmd_search.py
tpcli/teampass/__init__.py
tpcli/teampass/exceptions.py
tpcli/teampass/teampass.py