Metadata-Version: 1.1
Name: teampass-cli
Version: 0.0.10
Summary: Simple command line interface for Teampass
Home-page: https://github.com/verdel/teampass-cli
Author: Vadim Aleksandrov
Author-email: valeksandrov@me.com
License: MIT
Keywords: teampass-cli
Platform: UNKNOWN
Classifier: Environment :: Console
Classifier: Development Status :: 4 - Beta
Classifier: Intended Audience :: System Administrators
Classifier: License :: OSI Approved :: MIT License
Classifier: Natural Language :: English
Classifier: Programming Language :: Python :: 2
Classifier: Programming Language :: Python :: 2.7
Classifier: Programming Language :: Python :: 3
Classifier: Programming Language :: Python :: 3.3
Classifier: Programming Language :: Python :: 3.4
Classifier: Programming Language :: Python :: 3.5
